setup.py
timecandel_pos_forex_next3/__init__.py
timecandel_pos_forex_next3/timecandel_pos_forex_next3.py
timecandel_pos_forex_next3.egg-info/PKG-INFO
timecandel_pos_forex_next3.egg-info/SOURCES.txt
timecandel_pos_forex_next3.egg-info/dependency_links.txt
timecandel_pos_forex_next3.egg-info/not-zip-safe
timecandel_pos_forex_next3.egg-info/top_level.txt