Metadata-Version: 1.0
Name: timecandel-pos-forex-next3
Version: 1.2
Summary: timecandel_pos_forex_next3
Home-page: UNKNOWN
Author: omid
Author-email: UNKNOWN
License: UNKNOWN
Platform: UNKNOWN
